transformers_openai_api/__init__.py
transformers_openai_api/__main__.py
transformers_openai_api/app.py
transformers_openai_api/metrics.py
transformers_openai_api/models.py
transformers_openai_api/serve.py
transformers_openai_api-1.1.0.dist-info/LICENSE
transformers_openai_api-1.1.0.dist-info/METADATA
transformers_openai_api-1.1.0.dist-info/WHEEL
transformers_openai_api-1.1.0.dist-info/entry_points.txt
transformers_openai_api-1.1.0.dist-info/top_level.txt
transformers_openai_api-1.1.0.dist-info/RECORD
