Metadata-Version: 2.1
Name: transformers-openai-api
Version: 1.1.0
Summary: An OpenAI Completions API compatible server for NLP transformers models
Home-page: https://github.com/jquesnelle/transformers-openai-api/
Author: Jeffrey Quesnelle
Author-email: jq@jeffq.com
License: MIT
Platform: UNKNOWN
Classifier: Programming Language :: Python :: 3
Classifier: License :: OSI Approved :: MIT License
Classifier: Operating System :: OS Independent
License-File: LICENSE
Requires-Dist: transformers
Requires-Dist: accelerate
Requires-Dist: torch
Requires-Dist: Flask
